<?xml version="1.0" encoding="utf-8" standalone="no"?>
<!DOCTYPE paula SYSTEM "paula_feat.dtd">
<paula version="1.0">
<header paula_id="ogr040.Eulalie_wd_morph"/>
<featList xmlns:xlink="http://www.w3.org/1999/xlink" type="morph" xml:base="ogr040.Eulalie.wd.xml">
<feat xlink:href="#wd_0" value="sfn"/><!-- buona -->
<feat xlink:href="#wd_1" value="sfn"/><!-- pulcella -->
<feat xlink:href="#wd_2" value="indpsp3"/><!-- fut -->
<feat xlink:href="#wd_3" value="sfn"/><!-- eulalia -->
<feat xlink:href="#wd_4" value="smr"/><!-- bel -->
<feat xlink:href="#wd_5" value="indpqp3"/><!-- auret -->
<feat xlink:href="#wd_6" value="smr"/><!-- corps -->
<feat xlink:href="#wd_7" value="sfr"/><!-- bellezour -->
<feat xlink:href="#wd_8" value="sfr"/><!-- anima -->
<feat xlink:href="#wd_9" value="indpsp6"/><!-- voldrent -->
<feat xlink:href="#wd_10" value="3sfa"/><!-- la -->
<feat xlink:href="#wd_11" value="--"/><!-- veintre -->
<feat xlink:href="#wd_12" value="pmn"/><!-- li -->
<feat xlink:href="#wd_13" value="smr"/><!-- deo -->
<feat xlink:href="#wd_14" value="pmn"/><!-- inimi -->
<feat xlink:href="#wd_15" value="indpsp6"/><!-- voldrent -->
<feat xlink:href="#wd_16" value="3sfa"/><!-- la -->
<feat xlink:href="#wd_17" value="--"/><!-- faire -->
<feat xlink:href="#wd_18" value="smr"/><!-- diaule -->
<feat xlink:href="#wd_19" value="--"/><!-- servir -->
<feat xlink:href="#wd_20" value="3sfn"/><!-- elle -->
<feat xlink:href="#wd_21" value="--"/><!-- no -->
<feat xlink:href="#wd_22" value="--"/><!-- nt -->
<feat xlink:href="#wd_23" value="indpst3"/><!-- eskoltet -->
<feat xlink:href="#wd_24" value="pmr"/><!-- les -->
<feat xlink:href="#wd_25" value="pmr"/><!-- mals -->
<feat xlink:href="#wd_26" value="pmr"/><!-- conselliers -->
<feat xlink:href="#wd_27" value="--"/><!-- qu -->
<feat xlink:href="#wd_28" value="3sfn"/><!-- elle -->
<feat xlink:href="#wd_29" value="smr"/><!-- deo -->
<feat xlink:href="#wd_30" value="indpst3"/><!-- raneiet -->
<feat xlink:href="#wd_31" value="smn"/><!-- chi -->
<feat xlink:href="#wd_32" value="indpst3"/><!-- maent -->
<feat xlink:href="#wd_33" value="--"/><!-- sus -->
<feat xlink:href="#wd_34" value="--"/><!-- en -->
<feat xlink:href="#wd_35" value="smr"/><!-- ciel -->
<feat xlink:href="#wd_36" value="--"/><!-- ne -->
<feat xlink:href="#wd_37" value="--"/><!-- por -->
<feat xlink:href="#wd_38" value="smr"/><!-- or -->
<feat xlink:href="#wd_39" value="--"/><!-- ned -->
<feat xlink:href="#wd_40" value="smr"/><!-- argent -->
<feat xlink:href="#wd_41" value="--"/><!-- ne -->
<feat xlink:href="#wd_42" value="pmr"/><!-- paramenz -->
<feat xlink:href="#wd_43" value="--"/><!-- por -->
<feat xlink:href="#wd_44" value="sfr"/><!-- manatce -->
<feat xlink:href="#wd_45" value="sfr"/><!-- regiel -->
<feat xlink:href="#wd_46" value="--"/><!-- ne -->
<feat xlink:href="#wd_47" value="smr"/><!-- preiement -->
<feat xlink:href="#wd_48" value="sfn"/><!-- niule -->
<feat xlink:href="#wd_49" value="sfn"/><!-- cose -->
<feat xlink:href="#wd_50" value="--"/><!-- non -->
<feat xlink:href="#wd_51" value="3sfa"/><!-- la -->
<feat xlink:href="#wd_52" value="indpqp3"/><!-- pouret -->
<feat xlink:href="#wd_53" value="--"/><!-- omque -->
<feat xlink:href="#wd_54" value="--"/><!-- pleier -->
<feat xlink:href="#wd_55" value="sfn"/><!-- la -->
<feat xlink:href="#wd_56" value="sfn"/><!-- polle -->
<feat xlink:href="#wd_57" value="--"/><!-- sempre -->
<feat xlink:href="#wd_58" value="--"/><!-- non -->
<feat xlink:href="#wd_59" value="subipf3"/><!-- amast -->
<feat xlink:href="#wd_60" value="smr"/><!-- lo -->
<feat xlink:href="#wd_61" value="smr"/><!-- deo -->
<feat xlink:href="#wd_62" value="smr"/><!-- menestier -->
<feat xlink:href="#wd_63" value="--"/><!-- e -->
<feat xlink:href="#wd_64" value="--"/><!-- por -->
<feat xlink:href="#wd_65" value="snr"/><!-- o -->
<feat xlink:href="#wd_66" value="indpsp3"/><!-- fu -->
<feat xlink:href="#wd_67" value="sfn"/><!-- presentede -->
<feat xlink:href="#wd_68" value="smr"/><!-- maximiien -->
<feat xlink:href="#wd_69" value="smn"/><!-- chi -->
<feat xlink:href="#wd_70" value="smn"/><!-- rex -->
<feat xlink:href="#wd_71" value="indipf3"/><!-- eret -->
<feat xlink:href="#wd_72" value="--"/><!-- a -->
<feat xlink:href="#wd_73" value="pmr"/><!-- cels -->
<feat xlink:href="#wd_74" value="pmr"/><!-- dis -->
<feat xlink:href="#wd_75" value="--"/><!-- soure -->
<feat xlink:href="#wd_76" value="pmr"/><!-- pagiens -->
<feat xlink:href="#wd_77" value="3smn"/><!-- il -->
<feat xlink:href="#wd_78" value="3smi"/><!-- li -->
<feat xlink:href="#wd_79" value="indpst3"/><!-- enortet -->
<feat xlink:href="#wd_80" value="---"/><!-- dont -->
<feat xlink:href="#wd_81" value="3sfr"/><!-- lei -->
<feat xlink:href="#wd_82" value="--"/><!-- nonque -->
<feat xlink:href="#wd_83" value="indpst0"/><!-- chielt -->
<feat xlink:href="#wd_84" value="--"/><!-- qued -->
<feat xlink:href="#wd_85" value="3sfn"/><!-- elle -->
<feat xlink:href="#wd_86" value="subpst3"/><!-- fuiet -->
<feat xlink:href="#wd_87" value="smr"/><!-- lo -->
<feat xlink:href="#wd_88" value="smr"/><!-- nom -->
<feat xlink:href="#wd_89" value="smr"/><!-- christiien -->
<feat xlink:href="#wd_90" value="3sfn"/><!-- ell -->
<feat xlink:href="#wd_91" value="--"/><!-- ent -->
<feat xlink:href="#wd_92" value="indpst3"/><!-- adunet -->
<feat xlink:href="#wd_93" value="smr"/><!-- lo -->
<feat xlink:href="#wd_94" value="3smr"/><!-- suon -->
<feat xlink:href="#wd_95" value="smr"/><!-- element -->
<feat xlink:href="#wd_96" value="--"/><!-- melz -->
<feat xlink:href="#wd_97" value="con---3"/><!-- sostendreiet -->
<feat xlink:href="#wd_98" value="pmr"/><!-- les -->
<feat xlink:href="#wd_99" value="pmr"/><!-- empedementz -->
<feat xlink:href="#wd_100" value="--"/><!-- qu -->
<feat xlink:href="#wd_101" value="3sfn"/><!-- elle -->
<feat xlink:href="#wd_102" value="subipf3"/><!-- perdesse -->
<feat xlink:href="#wd_103" value="3sfr"/><!-- sa -->
<feat xlink:href="#wd_104" value="sfr"/><!-- virginitet -->
<feat xlink:href="#wd_105" value="--"/><!-- por -->
<feat xlink:href="#wd_106" value="snr"/><!-- o -->
<feat xlink:href="#wd_107" value="3sfr"/><!-- s -->
<feat xlink:href="#wd_108" value="indpqp3"/><!-- furet -->
<feat xlink:href="#wd_109" value="sfn"/><!-- morte -->
<feat xlink:href="#wd_110" value="--"/><!-- a -->
<feat xlink:href="#wd_111" value="sfr"/><!-- grand -->
<feat xlink:href="#wd_112" value="sfr"/><!-- honestet -->
<feat xlink:href="#wd_113" value="--"/><!-- enz -->
<feat xlink:href="#wd_114" value="--"/><!-- en -->
<feat xlink:href="#wd_115" value="smr"/><!-- l -->
<feat xlink:href="#wd_116" value="smr"/><!-- fou -->
<feat xlink:href="#wd_117" value="3sma"/><!-- lo -->
<feat xlink:href="#wd_118" value="indpsp6"/><!-- getterent -->
<feat xlink:href="#wd_119" value="--"/><!-- com -->
<feat xlink:href="#wd_120" value="subpst3"/><!-- arde -->
<feat xlink:href="#wd_121" value="--"/><!-- tost -->
<feat xlink:href="#wd_122" value="3sfn"/><!-- elle -->
<feat xlink:href="#wd_123" value="pfr"/><!-- colpes -->
<feat xlink:href="#wd_124" value="--"/><!-- non -->
<feat xlink:href="#wd_125" value="indpqp3"/><!-- auret -->
<feat xlink:href="#wd_126" value="--"/><!-- por -->
<feat xlink:href="#wd_127" value="snr"/><!-- o -->
<feat xlink:href="#wd_128" value="--"/><!-- no -->
<feat xlink:href="#wd_129" value="3sfr"/><!-- s -->
<feat xlink:href="#wd_130" value="indpsp3"/><!-- coist -->
<feat xlink:href="#wd_131" value="--"/><!-- a -->
<feat xlink:href="#wd_132" value="snr"/><!-- czo -->
<feat xlink:href="#wd_133" value="--"/><!-- no -->
<feat xlink:href="#wd_134" value="3smr"/><!-- s -->
<feat xlink:href="#wd_135" value="indpqp3"/><!-- voldret -->
<feat xlink:href="#wd_136" value="--"/><!-- concreidre -->
<feat xlink:href="#wd_137" value="smn"/><!-- li -->
<feat xlink:href="#wd_138" value="smn"/><!-- rex -->
<feat xlink:href="#wd_139" value="smn"/><!-- pagiens -->
<feat xlink:href="#wd_140" value="--"/><!-- ad -->
<feat xlink:href="#wd_141" value="sfr"/><!-- une -->
<feat xlink:href="#wd_142" value="sfr"/><!-- spede -->
<feat xlink:href="#wd_143" value="3sfi"/><!-- li -->
<feat xlink:href="#wd_144" value="indpqp3"/><!-- roveret -->
<feat xlink:href="#wd_145" value="--"/><!-- tolir -->
<feat xlink:href="#wd_146" value="smr"/><!-- lo -->
<feat xlink:href="#wd_147" value="smr"/><!-- chief -->
<feat xlink:href="#wd_148" value="sfn"/><!-- la -->
<feat xlink:href="#wd_149" value="sfn"/><!-- domnizelle -->
<feat xlink:href="#wd_150" value="sfr"/><!-- celle -->
<feat xlink:href="#wd_151" value="sfr"/><!-- kose -->
<feat xlink:href="#wd_152" value="--"/><!-- non -->
<feat xlink:href="#wd_153" value="indpsp3"/><!-- contredist -->
<feat xlink:href="#wd_154" value="indpsp3"/><!-- volt -->
<feat xlink:href="#wd_155" value="smr"/><!-- lo -->
<feat xlink:href="#wd_156" value="smr"/><!-- seule -->
<feat xlink:href="#wd_157" value="--"/><!-- lazsier -->
<feat xlink:href="#wd_158" value="--"/><!-- si -->
<feat xlink:href="#wd_159" value="indpst3"/><!-- ruovet -->
<feat xlink:href="#wd_160" value="smr"/><!-- krist -->
<feat xlink:href="#wd_161" value="--"/><!-- in -->
<feat xlink:href="#wd_162" value="sfr"/><!-- figure -->
<feat xlink:href="#wd_163" value="--"/><!-- de -->
<feat xlink:href="#wd_164" value="sfr"/><!-- colomb -->
<feat xlink:href="#wd_165" value="indpsp3"/><!-- volat -->
<feat xlink:href="#wd_166" value="--"/><!-- a -->
<feat xlink:href="#wd_167" value="smr"/><!-- ciel -->
<feat xlink:href="#wd_168" value="pmn"/><!-- tuit -->
<feat xlink:href="#wd_169" value="subpst4"/><!-- oram -->
<feat xlink:href="#wd_170" value="--"/><!-- que -->
<feat xlink:href="#wd_171" value="--"/><!-- per -->
<feat xlink:href="#wd_172" value="4pmr"/><!-- nos -->
<feat xlink:href="#wd_173" value="subpst3"/><!-- degnet -->
<feat xlink:href="#wd_174" value="--"/><!-- preier -->
<feat xlink:href="#wd_175" value="--"/><!-- qued -->
<feat xlink:href="#wd_176" value="subipf3"/><!-- auwisset -->
<feat xlink:href="#wd_177" value="--"/><!-- de -->
<feat xlink:href="#wd_178" value="4pmr"/><!-- nos -->
<feat xlink:href="#wd_179" value="smn"/><!-- christus -->
<feat xlink:href="#wd_180" value="sfr"/><!-- mercit -->
<feat xlink:href="#wd_181" value="--"/><!-- post -->
<feat xlink:href="#wd_182" value="sfr"/><!-- la -->
<feat xlink:href="#wd_183" value="--"/><!-- mort -->
<feat xlink:href="#wd_184" value="--"/><!-- et -->
<feat xlink:href="#wd_185" value="--"/><!-- a -->
<feat xlink:href="#wd_186" value="3smr"/><!-- lui -->
<feat xlink:href="#wd_187" value="4pmr"/><!-- nos -->
<feat xlink:href="#wd_188" value="subpst3"/><!-- laist -->
<feat xlink:href="#wd_189" value="--"/><!-- venir -->
<feat xlink:href="#wd_190" value="--"/><!-- par -->
<feat xlink:href="#wd_191" value="3sfr"/><!-- souwe -->
<feat xlink:href="#wd_192" value="sfr"/><!-- clementia -->
</featList>
</paula>