<?xml version="1.0" encoding="utf-8" standalone="no"?>
<!DOCTYPE paula SYSTEM "paula_mark.dtd">
<paula version="1.0">
<header paula_id="ogr040.PrVierge2_line"/>
<markList xmlns:xlink="http://www.w3.org/1999/xlink" type="line" xml:base="ogr040.PrVierge2.tok.xml">
<mark id="line_0" xlink:href="#xpointer(id('tok_0')/range-to(id('tok_15')))"/><!-- inhocannicirculo -->
<mark id="line_1" xlink:href="#xpointer(id('tok_16')/range-to(id('tok_30')))"/><!-- vitadaturseculo -->
<mark id="line_2" xlink:href="#xpointer(id('tok_31')/range-to(id('tok_46')))"/><!-- natonobisparvulo -->
<mark id="line_3" xlink:href="#xpointer(id('tok_47')/range-to(id('tok_60')))"/><!-- devirginemaria -->
<mark id="line_4" xlink:href="#xpointer(id('tok_61')/range-to(id('tok_75')))"/><!-- meiamicemeifiel -->
<mark id="line_5" xlink:href="#xpointer(id('tok_76')/range-to(id('tok_93')))"/><!-- laisatestarlogazel -->
<mark id="line_6" xlink:href="#xpointer(id('tok_94')/range-to(id('tok_108')))"/><!-- aprendetusonoel -->
<mark id="line_7" xlink:href="#xpointer(id('tok_109')/range-to(id('tok_117')))"/><!-- devirgine -->
<mark id="line_8" xlink:href="#xpointer(id('tok_118')/range-to(id('tok_132')))"/><!-- fonsdesuorivulo -->
<mark id="line_9" xlink:href="#xpointer(id('tok_133')/range-to(id('tok_149')))"/><!-- nasciturpropopulo -->
<mark id="line_10" xlink:href="#xpointer(id('tok_150')/range-to(id('tok_167')))"/><!-- nectomortisvinculo -->
<mark id="line_11" xlink:href="#xpointer(id('tok_168')/range-to(id('tok_176')))"/><!-- devirgine -->
<mark id="line_12" xlink:href="#xpointer(id('tok_177')/range-to(id('tok_195')))"/><!-- laislomdirechinousab -->
<mark id="line_13" xlink:href="#xpointer(id('tok_196')/range-to(id('tok_215')))"/><!-- queunoldiraisesnulgab -->
<mark id="line_14" xlink:href="#xpointer(id('tok_216')/range-to(id('tok_232')))"/><!-- moutnemissitabochab -->
<mark id="line_15" xlink:href="#xpointer(id('tok_233')/range-to(id('tok_241')))"/><!-- devirgine -->
<mark id="line_16" xlink:href="#xpointer(id('tok_242')/range-to(id('tok_261')))"/><!-- quodvetustassuffocat -->
<mark id="line_17" xlink:href="#xpointer(id('tok_262')/range-to(id('tok_278')))"/><!-- hocadvitamrevocat -->
<mark id="line_18" xlink:href="#xpointer(id('tok_279')/range-to(id('tok_295')))"/><!-- namsedeuscollocat -->
<mark id="line_19" xlink:href="#xpointer(id('tok_296')/range-to(id('tok_304')))"/><!-- devirgine -->
<mark id="line_20" xlink:href="#xpointer(id('tok_305')/range-to(id('tok_312')))"/><!-- sosabiat -->
<mark id="line_21" xlink:href="#xpointer(id('tok_313')/range-to(id('tok_331')))"/><!-- nochalcomsendesesper -->
<mark id="line_22" xlink:href="#xpointer(id('tok_332')/range-to(id('tok_350')))"/><!-- deusivenpernosmaner -->
<mark id="line_23" xlink:href="#xpointer(id('tok_351')/range-to(id('tok_364')))"/><!-- intevirgomaria -->
<mark id="line_24" xlink:href="#xpointer(id('tok_365')/range-to(id('tok_378')))"/><!-- sineviricopula -->
<mark id="line_25" xlink:href="#xpointer(id('tok_379')/range-to(id('tok_396')))"/><!-- floremdeditvirgula -->
<mark id="line_26" xlink:href="#xpointer(id('tok_397')/range-to(id('tok_412')))"/><!-- quimanetinsecula -->
<mark id="line_27" xlink:href="#xpointer(id('tok_413')/range-to(id('tok_421')))"/><!-- devirgine -->
<mark id="line_28" xlink:href="#xpointer(id('tok_422')/range-to(id('tok_441')))"/><!-- nonperdraivirginitat -->
<mark id="line_29" xlink:href="#xpointer(id('tok_442')/range-to(id('tok_462')))"/><!-- tostempsauraichastitat -->
<mark id="line_30" xlink:href="#xpointer(id('tok_463')/range-to(id('tok_479')))"/><!-- sicumesprofetizat -->
<mark id="line_31" xlink:href="#xpointer(id('tok_480')/range-to(id('tok_493')))"/><!-- poisvirgomaria -->
<mark id="line_32" xlink:href="#xpointer(id('tok_494')/range-to(id('tok_508')))"/><!-- summipatrifilio -->
<mark id="line_33" xlink:href="#xpointer(id('tok_509')/range-to(id('tok_523')))"/><!-- daturinpresepio -->
<mark id="line_34" xlink:href="#xpointer(id('tok_524')/range-to(id('tok_540')))"/><!-- sedvolentesmansio -->
<mark id="line_35" xlink:href="#tok_541"/><!-- e -->
<mark id="line_36" xlink:href="#xpointer(id('tok_542')/range-to(id('tok_561')))"/><!-- eusoilangelsgabriels -->
<mark id="line_37" xlink:href="#xpointer(id('tok_562')/range-to(id('tok_578')))"/><!-- aporvossalutfiels -->
<mark id="line_38" xlink:href="#xpointer(id('tok_579')/range-to(id('tok_593')))"/><!-- deusdesusdeucel -->
<mark id="line_39" xlink:href="#xpointer(id('tok_594')/range-to(id('tok_597')))"/><!-- inte -->
<mark id="line_40" xlink:href="#xpointer(id('tok_598')/range-to(id('tok_612')))"/><!-- animalimpositum -->
<mark id="line_41" xlink:href="#xpointer(id('tok_613')/range-to(id('tok_628')))"/><!-- veneraturagnitum -->
<mark id="line_42" xlink:href="#xpointer(id('tok_629')/range-to(id('tok_647')))"/><!-- huncinfantemgenitum -->
<mark id="line_43" xlink:href="#tok_648"/><!-- e -->
<mark id="line_44" xlink:href="#xpointer(id('tok_649')/range-to(id('tok_664')))"/><!-- cumlareinalenten -->
<mark id="line_45" xlink:href="#xpointer(id('tok_665')/range-to(id('tok_682')))"/><!-- silrespontampiamen -->
<mark id="line_46" xlink:href="#xpointer(id('tok_683')/range-to(id('tok_698')))"/><!-- acosiaausotalent -->
<mark id="line_47" xlink:href="#tok_699"/><!-- e -->
<mark id="line_48" xlink:href="#xpointer(id('tok_700')/range-to(id('tok_711')))"/><!-- obeatafemina -->
<mark id="line_49" xlink:href="#xpointer(id('tok_712')/range-to(id('tok_730')))"/><!-- cujusventrissarcina -->
<mark id="line_50" xlink:href="#xpointer(id('tok_731')/range-to(id('tok_746')))"/><!-- mundiluitcrimina -->
<mark id="line_51" xlink:href="#tok_747"/><!-- e -->
<mark id="line_52" xlink:href="#xpointer(id('tok_748')/range-to(id('tok_763')))"/><!-- cumlareinalauvit -->
<mark id="line_53" xlink:href="#xpointer(id('tok_764')/range-to(id('tok_780')))"/><!-- silametesiujauvit -->
<mark id="line_54" xlink:href="#xpointer(id('tok_781')/range-to(id('tok_796')))"/><!-- acosiaausochausit -->
<mark id="line_55" xlink:href="#xpointer(id('tok_797')/range-to(id('tok_800')))"/><!-- inte -->
<mark id="line_56" xlink:href="#xpointer(id('tok_801')/range-to(id('tok_815')))"/><!-- illilausetgloria -->
<mark id="line_57" xlink:href="#xpointer(id('tok_816')/range-to(id('tok_832')))"/><!-- honorvirtusgratia -->
<mark id="line_58" xlink:href="#xpointer(id('tok_833')/range-to(id('tok_847')))"/><!-- decusetvictoria -->
<mark id="line_59" xlink:href="#tok_848"/><!-- e -->
<mark id="line_60" xlink:href="#xpointer(id('tok_849')/range-to(id('tok_865')))"/><!-- tuesmesatjesalrei -->
<mark id="line_61" xlink:href="#xpointer(id('tok_866')/range-to(id('tok_881')))"/><!-- sicumtuoditocrei -->
<mark id="line_62" xlink:href="#xpointer(id('tok_882')/range-to(id('tok_897')))"/><!-- aluimedoemautrei -->
<mark id="line_63" xlink:href="#xpointer(id('tok_898')/range-to(id('tok_905')))"/><!-- egovirgo -->
<mark id="line_64" xlink:href="#xpointer(id('tok_906')/range-to(id('tok_922')))"/><!-- ancelasoidamrideu -->
<mark id="line_65" xlink:href="#xpointer(id('tok_923')/range-to(id('tok_939')))"/><!-- sicumtuoditocreeu -->
<mark id="line_66" xlink:href="#xpointer(id('tok_940')/range-to(id('tok_957')))"/><!-- maireseraidamrideu -->
<mark id="line_67" xlink:href="#xpointer(id('tok_958')/range-to(id('tok_962')))"/><!-- epois -->
<mark id="line_68" xlink:href="#xpointer(id('tok_963')/range-to(id('tok_983')))"/><!-- langelsesdeucelvengut -->
<mark id="line_69" xlink:href="#xpointer(id('tok_984')/range-to(id('tok_999')))"/><!-- eladompnalacreut -->
<mark id="line_70" xlink:href="#xpointer(id('tok_1000')/range-to(id('tok_1018')))"/><!-- pertalnesmeserumbut -->
<mark id="line_71" xlink:href="#xpointer(id('tok_1019')/range-to(id('tok_1027')))"/><!-- devirgine -->
<mark id="line_72" xlink:href="#xpointer(id('tok_1028')/range-to(id('tok_1045')))"/><!-- euvosaiditmontalan -->
<mark id="line_73" xlink:href="#xpointer(id('tok_1046')/range-to(id('tok_1060')))"/><!-- evosdiiatenavan -->
<mark id="line_74" xlink:href="#xpointer(id('tok_1061')/range-to(id('tok_1081')))"/><!-- chaquesversnousabnosjan -->
<mark id="line_75" xlink:href="#xpointer(id('tok_1082')/range-to(id('tok_1090')))"/><!-- devirgine -->
</markList>
</paula>