<?xml version="1.0" encoding="utf-8" standalone="no"?>
<!DOCTYPE paula SYSTEM "paula_feat.dtd">
<paula version="1.0">
<header paula_id="ogrsv040.Spons_line_correct"/>
<featList xmlns:xlink="http://www.w3.org/1999/xlink" type="line_correct" xml:base="ogrsv040.Spons.line.xml">
<feat xlink:href="#line_0" value="False"/><!--  sponsus -->
<feat xlink:href="#line_1" value="True"/><!--  adest sponsus qui est christus vigilate virgines -->
<feat xlink:href="#line_2" value="True"/><!--  pro adventu cuius gaudent et gaudebunt homines -->
<feat xlink:href="#line_3" value="True"/><!--  venit enim liberare gentium origines -->
<feat xlink:href="#line_4" value="False"/><!--  quas per primam sibi matrem subiugarunt demones -->
<feat xlink:href="#line_5" value="True"/><!--  hic est adam qui secundus per propheta dicitur -->
<feat xlink:href="#line_6" value="True"/><!--  per quem scelus primi ade a nobis diluitur -->
<feat xlink:href="#line_7" value="True"/><!--  hic pependit ut celesti patrie nos redderet -->
<feat xlink:href="#line_8" value="True"/><!--  ac de parte inimici liberos nos traheret -->
<feat xlink:href="#line_9" value="True"/><!--  venit sponsus qui nostrorum scelerum piacula -->
<feat xlink:href="#line_10" value="True"/><!--  morte lavit atque crucis sustulit patibula -->
<feat xlink:href="#line_11" value="False"/><!--  prudentes -->
<feat xlink:href="#line_12" value="True"/><!--  oiet virgines aiso que vos dirum -->
<feat xlink:href="#line_13" value="True"/><!--  aisex presen que vos comandarum -->
<feat xlink:href="#line_14" value="False"/><!--  atendet un espos jhesu salvaire a nom -->
<feat xlink:href="#line_15" value="False"/><!--  gaire no i dormet -->
<feat xlink:href="#line_16" value="True"/><!--  aisel espos que vos hor atendet -->
<feat xlink:href="#line_17" value="True"/><!--  venit en terra per los vostres pechet -->
<feat xlink:href="#line_18" value="True"/><!--  de la virgine en betleem fo net -->
<feat xlink:href="#line_19" value="True"/><!--  e flum jorda lavet e bateet -->
<feat xlink:href="#line_20" value="False"/><!--  gaire -->
<feat xlink:href="#line_21" value="True"/><!--  eu fo batut gablet e laidenjet -->
<feat xlink:href="#line_22" value="True"/><!--  sus e la crot batut e claufiget -->
<feat xlink:href="#line_23" value="True"/><!--  e u monument desoentre pauset -->
<feat xlink:href="#line_24" value="False"/><!--  gaire -->
<feat xlink:href="#line_25" value="True"/><!--  e resors es la scriptura o dii -->
<feat xlink:href="#line_26" value="False"/><!--  gabriels soi eu trames aici -->
<feat xlink:href="#line_27" value="True"/><!--  atendet lo que ja venra praici -->
<feat xlink:href="#line_28" value="False"/><!--  gaire -->
<feat xlink:href="#line_29" value="False"/><!--  fatue -->
<feat xlink:href="#line_30" value="True"/><!--  nos virgines que ad vos venimus -->
<feat xlink:href="#line_31" value="True"/><!--  negligenter oleum fudimus -->
<feat xlink:href="#line_32" value="True"/><!--  ad vos orare sorores cupimus -->
<feat xlink:href="#line_33" value="True"/><!--  ut et illas quibus nos credimus -->
<feat xlink:href="#line_34" value="False"/><!--  dolentas chaitivas trop i avem dormit -->
<feat xlink:href="#line_35" value="True"/><!--  nos comites huius itineris -->
<feat xlink:href="#line_36" value="True"/><!--  et sorores eiusdem generis -->
<feat xlink:href="#line_37" value="True"/><!--  quamvis male contigit miseris -->
<feat xlink:href="#line_38" value="True"/><!--  potestis nos reddere superis -->
<feat xlink:href="#line_39" value="False"/><!--  dolentas -->
<feat xlink:href="#line_40" value="True"/><!--  partimini lumen lampadibus -->
<feat xlink:href="#line_41" value="True"/><!--  pie sitis insipientibus -->
<feat xlink:href="#line_42" value="True"/><!--  pulse ne nos simus a foribus -->
<feat xlink:href="#line_43" value="True"/><!--  cum vos sponsus vocet in sedibus -->
<feat xlink:href="#line_44" value="False"/><!--  dolentas -->
<feat xlink:href="#line_45" value="False"/><!--  prudentes -->
<feat xlink:href="#line_46" value="True"/><!--  nos precari precamur amplius -->
<feat xlink:href="#line_47" value="True"/><!--  desinite sorores otius -->
<feat xlink:href="#line_48" value="True"/><!--  vobis enim nil erit melius -->
<feat xlink:href="#line_49" value="True"/><!--  dare preces pro hoc ulterius -->
<feat xlink:href="#line_50" value="False"/><!--  dolentas -->
<feat xlink:href="#line_51" value="True"/><!--  ac ite nunc ite celeriter -->
<feat xlink:href="#line_52" value="True"/><!--  ac vendentes rogate dulciter -->
<feat xlink:href="#line_53" value="True"/><!--  ut oleum vestris lampadibus -->
<feat xlink:href="#line_54" value="True"/><!--  dent equidem vobis inertibus -->
<feat xlink:href="#line_55" value="False"/><!--  dolentas -->
<feat xlink:href="#line_56" value="True"/><!--  a misere nos hic quid facimus -->
<feat xlink:href="#line_57" value="True"/><!--  vigilare numquid potuimus -->
<feat xlink:href="#line_58" value="True"/><!--  hunc laborem que nunc perferimus -->
<feat xlink:href="#line_59" value="False"/><!--  nobis nosmed contulimus -->
<feat xlink:href="#line_60" value="False"/><!--  dolentas -->
<feat xlink:href="#line_61" value="True"/><!--  et de nobis mercator otius -->
<feat xlink:href="#line_62" value="True"/><!--  quas habeat merces quas sotius -->
<feat xlink:href="#line_63" value="True"/><!--  oleum nunc querere venimus -->
<feat xlink:href="#line_64" value="True"/><!--  negligenter quod nosme fudimus -->
<feat xlink:href="#line_65" value="False"/><!--  dolentas -->
<feat xlink:href="#line_66" value="True"/><!--  de nostr oli queret nos a doner -->
<feat xlink:href="#line_67" value="True"/><!--  no n auret pont alet en achapter -->
<feat xlink:href="#line_68" value="True"/><!--  de us merchaans que lai veet ester -->
<feat xlink:href="#line_69" value="False"/><!--  dolentas -->
<feat xlink:href="#line_70" value="False"/><!--  mercatores -->
<feat xlink:href="#line_71" value="True"/><!--  domnas gentils no vos covent ester -->
<feat xlink:href="#line_72" value="True"/><!--  ni lojamen aici a demorer -->
<feat xlink:href="#line_73" value="True"/><!--  cosel queret no u vos poem doner -->
<feat xlink:href="#line_74" value="True"/><!--  queret lo deu chi vos pot coseler -->
<feat xlink:href="#line_75" value="True"/><!--  alet areir a vostras sinc seros -->
<feat xlink:href="#line_76" value="True"/><!--  e preiat las per deu lo glorios -->
<feat xlink:href="#line_77" value="True"/><!--  de oleo fasen socors a vos -->
<feat xlink:href="#line_78" value="True"/><!--  faites o tost que ja venra l espos -->
<feat xlink:href="#line_79" value="True"/><!--  a misere nos ad quid venimus -->
<feat xlink:href="#line_80" value="True"/><!--  nil est enim illut quod querimus -->
<feat xlink:href="#line_81" value="True"/><!--  fatatum est et nos videbimus -->
<feat xlink:href="#line_82" value="True"/><!--  ad nuptias numquam intrabimus -->
<feat xlink:href="#line_83" value="False"/><!--  dolentas -->
<feat xlink:href="#line_84" value="False"/><!--  modo veniat sponsus -->
<feat xlink:href="#line_85" value="True"/><!--  audi sponse voces plangentium -->
<feat xlink:href="#line_86" value="True"/><!--  aperire fac nobis ostium -->
<feat xlink:href="#line_87" value="True"/><!--  cum sotiis prebe remedium -->
<feat xlink:href="#line_88" value="False"/><!--  modo veniat sponsus christus -->
<feat xlink:href="#line_89" value="True"/><!--  amen dico vos ignosco nam caretis lumine -->
<feat xlink:href="#line_90" value="True"/><!--  quod qui perdunt procul pergunt huius aule limine -->
<feat xlink:href="#line_91" value="True"/><!--  alet chaitivas alet malaureas -->
<feat xlink:href="#line_92" value="True"/><!--  a tot jors mais vos so penas liureas -->
<feat xlink:href="#line_93" value="False"/><!--  en efern ora seret meneias -->
<feat xlink:href="#line_94" value="False"/><!--  modo accipiant eas demones et precipitentur in infernum -->
</featList>
</paula>