<?xml version="1.0" encoding="utf-8" standalone="no"?>
<!DOCTYPE paula SYSTEM "paula_feat.dtd">
<paula version="1.0">
<header paula_id="ogr.PrVierge3_wd_morph"/>
<featList xmlns:xlink="http://www.w3.org/1999/xlink" type="morph" xml:base="ogr.PrVierge3.wd.xml">
<feat xlink:href="#wd_0" value="---"/><!-- versus -->
<feat xlink:href="#wd_1" value="---"/><!-- sancte -->
<feat xlink:href="#wd_2" value="---"/><!-- marie -->
<feat xlink:href="#wd_3" value="---"/><!-- o -->
<feat xlink:href="#wd_4" value="sfn"/><!-- maria -->
<feat xlink:href="#wd_5" value="smr"/><!-- deu -->
<feat xlink:href="#wd_6" value="sfn"/><!-- maire -->
<feat xlink:href="#wd_7" value="smn"/><!-- deu -->
<feat xlink:href="#wd_8" value="2sfr"/><!-- t -->
<feat xlink:href="#wd_9" value="indpst3"/><!-- es -->
<feat xlink:href="#wd_10" value="---"/><!-- e -->
<feat xlink:href="#wd_11" value="smn"/><!-- fils -->
<feat xlink:href="#wd_12" value="---"/><!-- e -->
<feat xlink:href="#wd_13" value="smn"/><!-- paire -->
<feat xlink:href="#wd_14" value="sfn"/><!-- domna -->
<feat xlink:href="#wd_15" value="imp---2"/><!-- preia -->
<feat xlink:href="#wd_16" value="---"/><!-- per -->
<feat xlink:href="#wd_17" value="4pmr"/><!-- nos -->
<feat xlink:href="#wd_18" value="2smr"/><!-- to -->
<feat xlink:href="#wd_19" value="smr"/><!-- fil -->
<feat xlink:href="#wd_20" value="smr"/><!-- lo -->
<feat xlink:href="#wd_21" value="smr"/><!-- glorios -->
<feat xlink:href="#wd_22" value="---"/><!-- e -->
<feat xlink:href="#wd_23" value="smr"/><!-- lo -->
<feat xlink:href="#wd_24" value="smr"/><!-- pair -->
<feat xlink:href="#wd_25" value="---"/><!-- aissamen -->
<feat xlink:href="#wd_26" value="imp---2"/><!-- preia -->
<feat xlink:href="#wd_27" value="---"/><!-- per -->
<feat xlink:href="#wd_28" value="sfr"/><!-- tota -->
<feat xlink:href="#wd_29" value="sfr"/><!-- jen -->
<feat xlink:href="#wd_30" value="---"/><!-- e -->
<feat xlink:href="#wd_31" value="---"/><!-- c -->
<feat xlink:href="#wd_32" value="3smn"/><!-- el -->
<feat xlink:href="#wd_33" value="---"/><!-- no -->
<feat xlink:href="#wd_34" value="4pmr"/><!-- nos -->
<feat xlink:href="#wd_35" value="indpst3"/><!-- socor -->
<feat xlink:href="#wd_36" value="snn"/><!-- tornat -->
<feat xlink:href="#wd_37" value="4pmr"/><!-- nos -->
<feat xlink:href="#wd_38" value="indpst0"/><!-- es -->
<feat xlink:href="#wd_39" value="---"/><!-- a -->
<feat xlink:href="#wd_40" value="smr"/><!-- plor -->
<feat xlink:href="#wd_41" value="sfn"/><!-- eva -->
<feat xlink:href="#wd_42" value="indpsp3"/><!-- creet -->
<feat xlink:href="#wd_43" value="smr"/><!-- serpen -->
<feat xlink:href="#wd_44" value="smr"/><!-- un -->
<feat xlink:href="#wd_45" value="smr"/><!-- agel -->
<feat xlink:href="#wd_46" value="smr"/><!-- resplanden -->
<feat xlink:href="#wd_47" value="---"/><!-- per -->
<feat xlink:href="#wd_48" value="snr"/><!-- so -->
<feat xlink:href="#wd_49" value="4pmr"/><!-- nos -->
<feat xlink:href="#wd_50" value="---"/><!-- en -->
<feat xlink:href="#wd_51" value="indpst0"/><!-- vai -->
<feat xlink:href="#wd_52" value="---"/><!-- gen -->
<feat xlink:href="#wd_53" value="smn"/><!-- deus -->
<feat xlink:href="#wd_54" value="---"/><!-- n -->
<feat xlink:href="#wd_55" value="indpst3"/><!-- es -->
<feat xlink:href="#wd_56" value="smn"/><!-- om -->
<feat xlink:href="#wd_57" value="---"/><!-- veramen -->
<feat xlink:href="#wd_58" value="---"/><!-- car -->
<feat xlink:href="#wd_59" value="---"/><!-- de -->
<feat xlink:href="#wd_60" value="sfr"/><!-- femna -->
<feat xlink:href="#wd_61" value="indpsp3"/><!-- nasquet -->
<feat xlink:href="#wd_62" value="smn"/><!-- deus -->
<feat xlink:href="#wd_63" value="sfr"/><!-- la -->
<feat xlink:href="#wd_64" value="sfr"/><!-- femna -->
<feat xlink:href="#wd_65" value="indpsp3"/><!-- salvet -->
<feat xlink:href="#wd_66" value="---"/><!-- e -->
<feat xlink:href="#wd_67" value="---"/><!-- pre -->
<feat xlink:href="#wd_68" value="snr"/><!-- quo -->
<feat xlink:href="#wd_69" value="indpsp3"/><!-- nasquet -->
<feat xlink:href="#wd_70" value="smn"/><!-- hom -->
<feat xlink:href="#wd_71" value="---"/><!-- que -->
<feat xlink:href="#wd_72" value="smn"/><!-- garit -->
<feat xlink:href="#wd_73" value="---"/><!-- en -->
<feat xlink:href="#wd_74" value="subipf3"/><!-- fos -->
<feat xlink:href="#wd_75" value="smn"/><!-- hom -->
<feat xlink:href="#wd_76" value="sfn"/><!-- eva -->
<feat xlink:href="#wd_77" value="sfn"/><!-- moler -->
<feat xlink:href="#wd_78" value="smr"/><!-- adam -->
<feat xlink:href="#wd_79" value="---"/><!-- quar -->
<feat xlink:href="#wd_80" value="indpsp3"/><!-- creet -->
<feat xlink:href="#wd_81" value="smr"/><!-- lo -->
<feat xlink:href="#wd_82" value="smr"/><!-- setam -->
<feat xlink:href="#wd_83" value="4pmr"/><!-- nos -->
<feat xlink:href="#wd_84" value="indpsp3"/><!-- mes -->
<feat xlink:href="#wd_85" value="---"/><!-- en -->
<feat xlink:href="#wd_86" value="smr"/><!-- tal -->
<feat xlink:href="#wd_87" value="smr"/><!-- afan -->
<feat xlink:href="#wd_88" value="---"/><!-- per -->
<feat xlink:href="#wd_89" value="smr"/><!-- qu -->
<feat xlink:href="#wd_90" value="indpst4"/><!-- avem -->
<feat xlink:href="#wd_91" value="sfr"/><!-- set -->
<feat xlink:href="#wd_92" value="---"/><!-- e -->
<feat xlink:href="#wd_93" value="sfr"/><!-- fam -->
<feat xlink:href="#wd_94" value="sfn"/><!-- eva -->
<feat xlink:href="#wd_95" value="---"/><!-- mot -->
<feat xlink:href="#wd_96" value="indpsp3"/><!-- foleet -->
<feat xlink:href="#wd_97" value="---"/><!-- quar -->
<feat xlink:href="#wd_98" value="---"/><!-- de -->
<feat xlink:href="#wd_99" value="smr"/><!-- queu -->
<feat xlink:href="#wd_100" value="smr"/><!-- frut -->
<feat xlink:href="#wd_101" value="indpsp3"/><!-- manjet -->
<feat xlink:href="#wd_102" value="smr"/><!-- que -->
<feat xlink:href="#wd_103" value="smn"/><!-- deus -->
<feat xlink:href="#wd_104" value="3sfi"/><!-- li -->
<feat xlink:href="#wd_105" value="indpsp3"/><!-- devedet -->
<feat xlink:href="#wd_106" value="---"/><!-- e -->
<feat xlink:href="#wd_107" value="smr"/><!-- cel -->
<feat xlink:href="#wd_108" value="smn"/><!-- que -->
<feat xlink:href="#wd_109" value="sfr"/><!-- la -->
<feat xlink:href="#wd_110" value="indpsp3"/><!-- creet -->
<feat xlink:href="#wd_111" value="---"/><!-- e -->
<feat xlink:href="#wd_112" value="---"/><!-- c -->
<feat xlink:href="#wd_113" value="6pmn"/><!-- el -->
<feat xlink:href="#wd_114" value="---"/><!-- no -->
<feat xlink:href="#wd_115" value="3sma"/><!-- l -->
<feat xlink:href="#wd_116" value="---"/><!-- an -->
<feat xlink:href="#wd_117" value="subipf3"/><!-- crees -->
<feat xlink:href="#wd_118" value="---"/><!-- e -->
<feat xlink:href="#wd_119" value="---"/><!-- de -->
<feat xlink:href="#wd_120" value="smr"/><!-- u -->
<feat xlink:href="#wd_121" value="smr"/><!-- fruit -->
<feat xlink:href="#wd_122" value="---"/><!-- no -->
<feat xlink:href="#wd_123" value="subipf3"/><!-- manjes -->
<feat xlink:href="#wd_124" value="---"/><!-- ja -->
<feat xlink:href="#wd_125" value="---"/><!-- no -->
<feat xlink:href="#wd_126" value="indfut3"/><!-- murira -->
<feat xlink:href="#wd_127" value="smn"/><!-- hom -->
<feat xlink:href="#wd_128" value="smn"/><!-- chi -->
<feat xlink:href="#wd_129" value="subipf3"/><!-- ames -->
<feat xlink:href="#wd_130" value="4smr"/><!-- nostre -->
<feat xlink:href="#wd_131" value="smr"/><!-- don -->
<feat xlink:href="#wd_132" value="---"/><!-- mas -->
<feat xlink:href="#wd_133" value="---"/><!-- tan -->
<feat xlink:href="#wd_134" value="indpqp3"/><!-- fora -->
<feat xlink:href="#wd_135" value="---"/><!-- de -->
<feat xlink:href="#wd_136" value="sfr"/><!-- gen -->
<feat xlink:href="#wd_137" value="sfn"/><!-- ch -->
<feat xlink:href="#wd_138" value="indpqp3"/><!-- avera -->
<feat xlink:href="#wd_139" value="smr"/><!-- garimen -->
<feat xlink:href="#wd_140" value="pmn"/><!-- cil -->
<feat xlink:href="#wd_141" value="pmn"/><!-- chi -->
<feat xlink:href="#wd_142" value="pmn"/><!-- perdut -->
<feat xlink:href="#wd_143" value="indfut6"/><!-- seran -->
<feat xlink:href="#wd_144" value="---"/><!-- ja -->
<feat xlink:href="#wd_145" value="---"/><!-- per -->
<feat xlink:href="#wd_146" value="sfr"/><!-- re -->
<feat xlink:href="#wd_147" value="---"/><!-- no -->
<feat xlink:href="#wd_148" value="indpqp6"/><!-- foran -->
<feat xlink:href="#wd_149" value="smn"/><!-- adam -->
<feat xlink:href="#wd_150" value="indpsp3"/><!-- menjet -->
<feat xlink:href="#wd_151" value="smr"/><!-- lo -->
<feat xlink:href="#wd_152" value="smr"/><!-- fruit -->
<feat xlink:href="#wd_153" value="---"/><!-- per -->
<feat xlink:href="#wd_154" value="smr"/><!-- que -->
<feat xlink:href="#wd_155" value="indpsp4"/><!-- fom -->
<feat xlink:href="#wd_156" value="pmn"/><!-- tuit -->
<feat xlink:href="#wd_157" value="pmn"/><!-- perdut -->
<feat xlink:href="#wd_158" value="smn"/><!-- adam -->
<feat xlink:href="#wd_159" value="---"/><!-- no -->
<feat xlink:href="#wd_160" value="indpsp3"/><!-- creet -->
<feat xlink:href="#wd_161" value="smr"/><!-- deu -->
<feat xlink:href="#wd_162" value="---"/><!-- a -->
<feat xlink:href="#wd_163" value="pmr"/><!-- tot -->
<feat xlink:href="#wd_164" value="4pmr"/><!-- nos -->
<feat xlink:href="#wd_165" value="---"/><!-- en -->
<feat xlink:href="#wd_166" value="indpst0"/><!-- vai -->
<feat xlink:href="#wd_167" value="---"/><!-- greu -->
<feat xlink:href="#wd_168" value="smn"/><!-- deus -->
<feat xlink:href="#wd_169" value="indpsp3"/><!-- receubt -->
<feat xlink:href="#wd_170" value="---"/><!-- per -->
<feat xlink:href="#wd_171" value="3smr"/><!-- lui -->
<feat xlink:href="#wd_172" value="sfr"/><!-- mort -->
<feat xlink:href="#wd_173" value="---"/><!-- e -->
<feat xlink:href="#wd_174" value="sfr"/><!-- la -->
<feat xlink:href="#wd_175" value="sfr"/><!-- crot -->
<feat xlink:href="#wd_176" value="---"/><!-- a -->
<feat xlink:href="#wd_177" value="smr"/><!-- gran -->
<feat xlink:href="#wd_178" value="smr"/><!-- tort -->
<feat xlink:href="#wd_179" value="---"/><!-- e -->
<feat xlink:href="#wd_180" value="indpsp3"/><!-- resors -->
<feat xlink:href="#wd_181" value="---"/><!-- a -->
<feat xlink:href="#wd_182" value="smr"/><!-- l -->
<feat xlink:href="#wd_183" value="smr"/><!-- tert -->
<feat xlink:href="#wd_184" value="smr"/><!-- dia -->
<feat xlink:href="#wd_185" value="---"/><!-- si -->
<feat xlink:href="#wd_186" value="---"/><!-- cum -->
<feat xlink:href="#wd_187" value="snr"/><!-- o -->
<feat xlink:href="#wd_188" value="indpst3"/><!-- dii -->
<feat xlink:href="#wd_189" value="sfn"/><!-- maria -->
<feat xlink:href="#wd_190" value="---"/><!-- a -->
<feat xlink:href="#wd_191" value="pmr"/><!-- ut -->
<feat xlink:href="#wd_192" value="pmr"/><!-- apostols -->
<feat xlink:href="#wd_193" value="indpsp3"/><!-- cumtet -->
<feat xlink:href="#wd_194" value="---"/><!-- e -->
<feat xlink:href="#wd_195" value="indpsp3"/><!-- dis -->
<feat xlink:href="#wd_196" value="---"/><!-- c -->
<feat xlink:href="#wd_197" value="---"/><!-- ap -->
<feat xlink:href="#wd_198" value="smr"/><!-- deu -->
<feat xlink:href="#wd_199" value="indpsp3"/><!-- parlet -->
<feat xlink:href="#wd_200" value="---"/><!-- qu -->
<feat xlink:href="#wd_201" value="---"/><!-- e -->
<feat xlink:href="#wd_202" value="smr"/><!-- u -->
<feat xlink:href="#wd_203" value="smr"/><!-- poi -->
<feat xlink:href="#wd_204" value="---"/><!-- de -->
<feat xlink:href="#wd_205" value="sfr"/><!-- galilea -->
<feat xlink:href="#wd_206" value="smr"/><!-- viu -->
<feat xlink:href="#wd_207" value="3sma"/><!-- lo -->
<feat xlink:href="#wd_208" value="indfut4"/><!-- verem -->
<feat xlink:href="#wd_209" value="---"/><!-- angera -->
<feat xlink:href="#wd_210" value="sfn"/><!-- vida -->
<feat xlink:href="#wd_211" value="sfn"/><!-- qui -->
<feat xlink:href="#wd_212" value="sfr"/><!-- mort -->
<feat xlink:href="#wd_213" value="indpsp3"/><!-- aucis -->
<feat xlink:href="#wd_214" value="4pmr"/><!-- nos -->
<feat xlink:href="#wd_215" value="indpsp3"/><!-- donet -->
<feat xlink:href="#wd_216" value="smr"/><!-- paradis -->
<feat xlink:href="#wd_217" value="sfr"/><!-- gloria -->
<feat xlink:href="#wd_218" value="---"/><!-- aisamen -->
<feat xlink:href="#wd_219" value="4pmr"/><!-- nos -->
<feat xlink:href="#wd_220" value="subpst3"/><!-- do -->
<feat xlink:href="#wd_221" value="smn"/><!-- deus -->
<feat xlink:href="#wd_222" value="---"/><!-- veramen -->
</featList>
</paula>